paraty_commit_jlvillada/.pre-commit-config.yaml
paraty_commit_jlvillada/__init__.py
paraty_commit_jlvillada/mypy.ini
paraty_commit_jlvillada/precommit.py
paraty_commit_jlvillada/pylintrc
paraty_commit_jlvillada-0.1.35.dist-info/LICENSE
paraty_commit_jlvillada-0.1.35.dist-info/METADATA
paraty_commit_jlvillada-0.1.35.dist-info/WHEEL
paraty_commit_jlvillada-0.1.35.dist-info/entry_points.txt
paraty_commit_jlvillada-0.1.35.dist-info/top_level.txt
paraty_commit_jlvillada-0.1.35.dist-info/RECORD
