Metadata-Version: 2.1
Name: paraty-commit-jlvillada
Version: 0.1.35
Summary: Una biblioteca personalizada
Author: José Luis Villada
Author-email: jlvillada@paratytech.com
License-File: LICENSE
Requires-Dist: colorama
